Workbook

Sheet Sales Data
A1: Month | B1: Sales Channel | C1: Product | D1: Units Sold | E1: Selling Price | F1: Cost per Unit | G1: Revenue | H1: Profit
A2: Jan | B2: Website | C2: Laptop Stand | D2: 35 | E2: 1200 | F2: 700 | G2: =D2*E2 | H2: =G2-D2*F2
A3: Jan | B3: Instagram | C3: Desk Lamp | D3: 28 | E3: 1800 | F3: 1000 | G3: =D3*E3 | H3: =G3-D3*F3
A4: Jan | B4: Referral | C4: Keyboard | D4: 20 | E4: 2500 | F4: 1500 | G4: =D4*E4 | H4: =G4-D4*F4
A5: Feb | B5: Website | C5: Laptop Stand | D5: 42 | E5: 1200 | F5: 700 | G5: =D5*E5 | H5: =G5-D5*F5
A6: Feb | B6: Instagram | C6: Mouse | D6: 55 | E6: 900 | F6: 500 | G6: =D6*E6 | H6: =G6-D6*F6
A7: Feb | B7: Referral | C7: Keyboard | D7: 24 | E7: 2500 | F7: 1500 | G7: =D7*E7 | H7: =G7-D7*F7
A8: Mar | B8: Website | C8: Desk Lamp | D8: 38 | E8: 1800 | F8: 1000 | G8: =D8*E8 | H8: =G8-D8*F8
A9: Mar | B9: Instagram | C9: Keyboard | D9: 31 | E9: 2500 | F9: 1500 | G9: =D9*E9 | H9: =G9-D9*F9
A10: Mar | B10: Referral | C10: Mouse | D10: 47 | E10: 900 | F10: 500 | G10: =D10*E10 | H10: =G10-D10*F10
A11: Apr | B11: Website | C11: Laptop Stand | D11: 50 | E11: 1200 | F11: 700 | G11: =D11*E11 | H11: =G11-D11*F11
A12: Apr | B12: Instagram | C12: Desk Lamp | D12: 34 | E12: 1800 | F12: 1000 | G12: =D12*E12 | H12: =G12-D12*F12
A13: Apr | B13: Referral | C13: Keyboard | D13: 29 | E13: 2500 | F13: 1500 | G13: =D13*E13 | H13: =G13-D13*F13

Sheet Dashboard
A1: Sales & Profit Analysis Dashboard
A3: Total Revenue | B3: =SUM('Sales Data'!G2:G13) | D3: Month | E3: Revenue | F3: Profit
A4: Total Profit | B4: =SUM('Sales Data'!H2:H13) | D4: Jan | E4: =SUMIF('Sales Data'!A$2:A$13,D4,'Sales Data'!G$2:G$13) | F4: =SUMIF('Sales Data'!A$2:A$13,D4,'Sales Data'!H$2:H$13)
A5: Total Units Sold | B5: =SUM('Sales Data'!D2:D13) | D5: Feb | E5: =SUMIF('Sales Data'!A$2:A$13,D5,'Sales Data'!G$2:G$13) | F5: =SUMIF('Sales Data'!A$2:A$13,D5,'Sales Data'!H$2:H$13)
A6: Average Profit / Unit | B6: =B4/B5 | D6: Mar | E6: =SUMIF('Sales Data'!A$2:A$13,D6,'Sales Data'!G$2:G$13) | F6: =SUMIF('Sales Data'!A$2:A$13,D6,'Sales Data'!H$2:H$13)
D7: Apr | E7: =SUMIF('Sales Data'!A$2:A$13,D7,'Sales Data'!G$2:G$13) | F7: =SUMIF('Sales Data'!A$2:A$13,D7,'Sales Data'!H$2:H$13)
